baja/Client.py
baja/Collection.py
baja/Downloader.py
baja/Filter.py
baja/Interfaces.py
baja/Project.py
baja/Utils.py
baja/__init__.py
baja-0.0.5.dist-info/METADATA
baja-0.0.5.dist-info/WHEEL
baja-0.0.5.dist-info/top_level.txt
baja-0.0.5.dist-info/RECORD
