Metadata-Version: 2.1
Name: baja
Version: 0.0.5
Summary: Streaming video data via networks
Author: Ivan Mihajlov
Author-email: <ivan.mihajlov2703@gmail.com>
Keywords: python,requests,CDN
Classifier: Development Status :: 1 - Planning
Classifier: Intended Audience :: Developers
Classifier: Programming Language :: Python :: 3
Classifier: Operating System :: Unix
Classifier: Operating System :: MacOS :: MacOS X
Classifier: Operating System :: Microsoft :: Windows
Requires-Dist: requests
